MANIFEST.in
README.rst
base.cfg
buildout.cfg
publiccode.yml
requirements.txt
setup.py
test-5.0.x.cfg
test-5.1.x.cfg
test-5.2.x.cfg
test-6.0.x.cfg
tox.ini
docs/HISTORY.rst
docs/INSTALL.txt
docs/LICENSE.GPL
docs/LICENSE.txt
docs/rer-logo.png
rer/__init__.py
rer.portlet.advanced_static.egg-info/PKG-INFO
rer.portlet.advanced_static.egg-info/SOURCES.txt
rer.portlet.advanced_static.egg-info/dependency_links.txt
rer.portlet.advanced_static.egg-info/entry_points.txt
rer.portlet.advanced_static.egg-info/namespace_packages.txt
rer.portlet.advanced_static.egg-info/not-zip-safe
rer.portlet.advanced_static.egg-info/requires.txt
rer.portlet.advanced_static.egg-info/top_level.txt
rer/portlet/__init__.py
rer/portlet/advanced_static/__init__.py
rer/portlet/advanced_static/advanced_static.css
rer/portlet/advanced_static/configure.zcml
rer/portlet/advanced_static/exportimport.py
rer/portlet/advanced_static/i18n.sh
rer/portlet/advanced_static/rerportletadvancedstatic.pt
rer/portlet/advanced_static/rerportletadvancedstatic.py
rer/portlet/advanced_static/upgrades.py
rer/portlet/advanced_static/upgrades.zcml
rer/portlet/advanced_static/vocabulary.py
rer/portlet/advanced_static/i18n/plone-it.po
rer/portlet/advanced_static/i18n/plone-nl.po
rer/portlet/advanced_static/locales/rer.portlet.advanced_static.pot
rer/portlet/advanced_static/locales/it/LC_MESSAGES/rer.portlet.advanced_static.mo
rer/portlet/advanced_static/locales/it/LC_MESSAGES/rer.portlet.advanced_static.po
rer/portlet/advanced_static/locales/nl/LC_MESSAGES/rer.portlet.advanced_static.mo
rer/portlet/advanced_static/locales/nl/LC_MESSAGES/rer.portlet.advanced_static.po
rer/portlet/advanced_static/profiles/default/advanced_static-various.txt
rer/portlet/advanced_static/profiles/default/metadata.xml
rer/portlet/advanced_static/profiles/default/portlets.xml
rer/portlet/advanced_static/profiles/default/registry.xml
rer/portlet/advanced_static/profiles/uninstall/portlets.xml
rer/portlet/advanced_static/profiles/uninstall/registry.xml
rer/portlet/advanced_static/tests/__init__.py
rer/portlet/advanced_static/tests/base.py
rer/portlet/advanced_static/tests/test_portlet.py